Flask_GoogleRecaptcha-0.5.8.dist-info/METADATA
Flask_GoogleRecaptcha-0.5.8.dist-info/RECORD
Flask_GoogleRecaptcha-0.5.8.dist-info/WHEEL
Flask_GoogleRecaptcha-0.5.8.dist-info/top_level.txt
Flask_GoogleRecaptcha-0.5.8.dist-info/zip-safe
flask_google_recaptcha/__init__.py
