Metadata-Version: 2.1
Name: Flask-GoogleRecaptcha
Version: 0.5.8
Summary: The working Google ReCaptcha implementation for Flask without Flask-WTF
Home-page: https://github.com/AndersonFirmino/flask-google-recaptcha
Author: Anderson Araujo (coderpy)
Author-email: anderson.araujoprog@gmail.com
License: MIT
Download-URL: http://github.com/AndersonFirmino/flask-google-recaptcha/tarball/master
Keywords: flask,recaptcha,validate,google,google app engine,not a robot
Platform: any
Classifier: Environment :: Web Environment
Classifier: Intended Audience :: Developers
Classifier: License :: OSI Approved :: BSD License
Classifier: Operating System :: OS Independent
Classifier: Programming Language :: Python
Classifier: Programming Language :: Python :: 2
Classifier: Programming Language :: Python :: 2.6
Classifier: Programming Language :: Python :: 2.7
Classifier: Programming Language :: Python :: 3
Classifier: Programming Language :: Python :: 3.3
Classifier: Programming Language :: Python :: 3.4
Classifier: Programming Language :: Python :: 3.5
Classifier: Programming Language :: Python :: 3.6
Classifier: Topic :: Internet :: WWW/HTTP :: Dynamic Content
Classifier: Topic :: Software Development :: Libraries :: Python Modules
Requires-Dist: flask
Requires-Dist: jinja2
